{
  "main": {
    "id": "2d1fb875f7436850",
    "type": "split",
    "children": [
      {
        "id": "34eb04b5af3b1f11",
        "type": "tabs",
        "children": [
          {
            "id": "dc00275eb6627159",
            "type": "leaf",
            "state": {
              "type": "markdown",
              "state": {
                "file": "Thoughts/Old Ideas, New Opportunities.md",
                "mode": "source",
                "source": false
              }
            }
          },
          {
            "id": "009b2dbce36c4daf",
            "type": "leaf",
            "state": {
              "type": "markdown",
              "state": {
                "file": "Articles/Next in Tech - Apr. 1, 2023.md",
                "mode": "source",
                "source": false
              }
            }
          },
          {
            "id": "4c90fa13380d88c9",
            "type": "leaf",
            "state": {
              "type": "markdown",
              "state": {
                "file": "Thoughts/Protocols for AI Data Retrieval.md",
                "mode": "source",
                "source": false
              }
            }
          },
          {
            "id": "22115b1e9c5773b3",
            "type": "leaf",
            "state": {
              "type": "markdown",
              "state": {
                "file": "Thoughts/Notes on Farcaster Clients.md",
                "mode": "source",
                "source": false
              }
            }
          },
          {
            "id": "e3c716bbc6ab6487",
            "type": "leaf",
            "state": {
              "type": "markdown",
              "state": {
                "file": "Thoughts/AirPod World.md",
                "mode": "source",
                "source": false
              }
            }
          }
        ],
        "currentTab": 2
      }
    ],
    "direction": "vertical"
  },
  "left": {
    "id": "cb54a30459dff393",
    "type": "split",
    "children": [
      {
        "id": "931fcc1d38a8d6b7",
        "type": "tabs",
        "children": [
          {
            "id": "89c7a0a002a266c9",
            "type": "leaf",
            "state": {
              "type": "file-explorer",
              "state": {
                "sortOrder": "alphabetical"
              }
            }
          },
          {
            "id": "fbae400d41a8c49d",
            "type": "leaf",
            "state": {
              "type": "search",
              "state": {
                "query": "",
                "matchingCase": false,
                "explainSearch": false,
                "collapseAll": false,
                "extraContext": false,
                "sortOrder": "alphabetical"
              }
            }
          }
        ]
      }
    ],
    "direction": "horizontal",
    "width": 249.5
  },
  "right": {
    "id": "befe45d23acc61ce",
    "type": "split",
    "children": [
      {
        "id": "74cdec15d722ac70",
        "type": "tabs",
        "children": [
          {
            "id": "9b1e7fcbb32b1660",
            "type": "leaf",
            "state": {
              "type": "backlink",
              "state": {
                "file": "Thoughts/Protocols for AI Data Retrieval.md",
                "collapseAll": true,
                "extraContext": false,
                "sortOrder": "alphabetical",
                "showSearch": false,
                "searchQuery": "",
                "backlinkCollapsed": false,
                "unlinkedCollapsed": true
              }
            }
          }
        ]
      }
    ],
    "direction": "horizontal",
    "width": 300,
    "collapsed": true
  },
  "left-ribbon": {
    "hiddenItems": {
      "switcher:Open quick switcher": false,
      "graph:Open graph view": false,
      "canvas:Create new canvas": false,
      "command-palette:Open command palette": false,
      "markdown-importer:Open format converter": false
    }
  },
  "active": "4c90fa13380d88c9",
  "lastOpenFiles": [
    "Thoughts/Old Ideas, New Opportunities.md",
    "Thoughts/Notes on Farcaster Clients.md",
    "Thoughts/AirPod World.md",
    "Articles/Next in Tech - Apr. 8, 2023.md",
    "Media/SubstackNotesFeature.png",
    "Media/FarcasterEmbedsDiscussion.png",
    "Media/FarcasterEmbedsDiscussion.webp",
    "Media/WWDC2023.png",
    "Media/SubstackNotesFeature.webp",
    "Articles/Next in Tech - Apr. 1, 2023.md",
    "Thoughts/Protocols for AI Data Retrieval.md",
    "Media/NextInTechApr82023.png",
    "Articles/Product Launch NFTs.md",
    "Media/ProductLaunchNFTs.png",
    "Articles/The Boom of Farcaster's Developer Community.md",
    "Articles/The Wallet of Tomorrow.md",
    "Articles/User AI-gency.md",
    "Articles/Tools for action.md",
    "Articles/Next in Tech - Feb. 11, 2023.md",
    "Articles/Next in Tech - Mar. 20, 2023.md",
    "Articles/Next in Tech - Mar. 25, 2023.md",
    "Articles/Next in Tech - Mar. 4, 2023.md",
    "Articles/Next in Tech - Feb. 18, 2023.md",
    "Articles/Next in Tech - Feb. 4, 2023.md",
    "Articles/My Summer at Chapter One.md",
    "Articles/It's Time To Rebuild the Internet.md",
    "Articles/How I ended up spending all summer building a Chrome extension.md",
    "Articles/Building a Digital Garden.md",
    "Articles/2022 Recap.md",
    "Articles/Going Down the Rabbit Hole.md",
    "Articles/LEGO Blocks for the Web.md",
    "Articles/Next in Tech - Jan. 28, 2023.md",
    "Media/ChainstoryScreenshot.png",
    "Media/YupScreenshot.png",
    "Media/ChainstoryScreenshot.webp"
  ]
}